README.rst
setup.py
flynn/__init__.py
flynn/data.py
flynn/decoder.py
flynn/encoder.py
flynn/tool.py
flynn/utils.py
flynn.egg-info/PKG-INFO
flynn.egg-info/SOURCES.txt
flynn.egg-info/dependency_links.txt
flynn.egg-info/top_level.txt