Metadata-Version: 1.1
Name: flynn
Version: 1.0.0b2
Summary: Simple decoder and encoder for CBOR
Home-page: https://github.com/fritz0705/flynn.git
Author: Fritz Grimpen
Author-email: fritz@grimpen.net
License: http://opensource.org/licenses/MIT
Platform: UNKNOWN
Classifier: Development Status :: 4 - Beta
Classifier: Environment :: Web Environment
Classifier: License :: OSI Approved :: MIT License
Classifier: Programming Language :: Python :: 2.7
Classifier: Programming Language :: Python :: 3
Classifier: Topic :: System :: Networking
